tauro/__init__.py
tauro/cli/__init__.py
tauro/cli/cli.py
tauro/cli/config.py
tauro/cli/core.py
tauro/cli/error_analyzer.py
tauro/cli/execution.py
tauro/cli/formatters.py
tauro/cli/LICENSE
tauro/cli/README.md
tauro/cli/rich_logger.py
tauro/cli/schema_formatter.py
tauro/cli/template.py
tauro/cli/validators.py
tauro/config/__init__.py
tauro/config/context_loader.py
tauro/config/contexts.py
tauro/config/exceptions.py
tauro/config/interpolator.py
tauro/config/LICENSE
tauro/config/loaders.py
tauro/config/providers.py
tauro/config/README.md
tauro/config/session.py
tauro/config/validators.py
tauro/exec/__init__.py
tauro/exec/commands.py
tauro/exec/dependency_resolver.py
tauro/exec/executor.py
tauro/exec/feature_store_executor.py
tauro/exec/feature_store_integration.py
tauro/exec/import_security.py
tauro/exec/LICENSE
tauro/exec/ml_node_validator.py
tauro/exec/mlflow_node_executor.py
tauro/exec/mlops_auto_config.py
tauro/exec/mlops_executor_mixin.py
tauro/exec/mlops_integration.py
tauro/exec/node_executor.py
tauro/exec/pipeline_state.py
tauro/exec/pipeline_validator.py
tauro/exec/README.md
tauro/exec/resilience.py
tauro/exec/resource_manager.py
tauro/exec/resource_pool.py
tauro/exec/utils.py
tauro/feature_store/__init__.py
tauro/feature_store/base.py
tauro/feature_store/connection_pool.py
tauro/feature_store/data_source.py
tauro/feature_store/exceptions.py
tauro/feature_store/hybrid/__init__.py
tauro/feature_store/hybrid/store.py
tauro/feature_store/materialized/__init__.py
tauro/feature_store/materialized/store.py
tauro/feature_store/online/__init__.py
tauro/feature_store/online/store.py
tauro/feature_store/README.md
tauro/feature_store/schema/__init__.py
tauro/feature_store/schema/feature_schema.py
tauro/feature_store/source_selection_policy.py
tauro/feature_store/validators.py
tauro/feature_store/virtualized/__init__.py
tauro/feature_store/virtualized/store.py
tauro/io/__init__.py
tauro/io/base.py
tauro/io/constants.py
tauro/io/context_manager.py
tauro/io/exceptions.py
tauro-0.1.5.dist-info/entry_points.txt
tauro-0.1.5.dist-info/licenses/LICENSE
tauro-0.1.5.dist-info/METADATA
tauro-0.1.5.dist-info/WHEEL
tauro-0.1.5.dist-info/RECORD
