Metadata-Version: 2.4
Name: tauro
Version: 0.1.5
Summary: Tauro - Data pipeline framework for batch, streaming, and hybrid workflows
License: MIT
License-File: LICENSE
Keywords: data-pipeline,etl,spark,streaming,orchestration,workflow
Author: Faustino Lopez Ramos
Author-email: faustinolopezramos@gmail.com
Requires-Python: >=3.10,<4.0
Classifier: Development Status :: 4 - Beta
Classifier: Environment :: Console
Classifier: Intended Audience :: Developers
Classifier: License :: OSI Approved :: MIT License
Classifier: Operating System :: OS Independent
Classifier: Programming Language :: Python :: 3
Classifier: Programming Language :: Python :: 3.10
Classifier: Programming Language :: Python :: 3.11
Classifier: Programming Language :: Python :: 3.12
Classifier: Programming Language :: Python :: 3.13
Classifier: Programming Language :: Python :: 3.14
Classifier: Topic :: Software Development :: Libraries
Classifier: Topic :: System :: Systems Administration
Provides-Extra: all
Provides-Extra: api
Provides-Extra: database
Provides-Extra: mlops
Provides-Extra: monitoring
Provides-Extra: optimization
Provides-Extra: spark
Requires-Dist: APScheduler (>=3.10.0,<4.0.0) ; extra == "api" or extra == "all"
Requires-Dist: PyYAML (>=6.0,<7.0)
Requires-Dist: cachetools (>=5.3.0,<6.0.0) ; extra == "api" or extra == "all"
Requires-Dist: croniter (>=2.0.0,<3.0.0) ; extra == "api" or extra == "all"
Requires-Dist: databricks-connect (>=14.0.0,<15.0.0) ; extra == "mlops" or extra == "all"
Requires-Dist: fastapi (>=0.100.0,<0.101.0) ; extra == "api" or extra == "all"
Requires-Dist: loguru (>=0.7.0,<0.8.0)
Requires-Dist: mlflow (>=2.10.0,<3.0.0) ; extra == "mlops" or extra == "all"
Requires-Dist: motor (>=3.3.0,<4.0.0) ; extra == "api" or extra == "all"
Requires-Dist: numpy (>=1.24.0,<2.0.0) ; extra == "optimization" or extra == "all"
Requires-Dist: pandas (>=2.0.0,<3.0.0)
Requires-Dist: prometheus-client (>=0.17.0,<0.18.0) ; extra == "monitoring" or extra == "all"
Requires-Dist: psycopg2-binary (>=2.9.0,<3.0.0) ; extra == "database" or extra == "all"
Requires-Dist: pyarrow (>=12.0.0,<13.0.0) ; extra == "spark" or extra == "all"
Requires-Dist: pydantic (>=2.0.0,<3.0.0) ; extra == "api" or extra == "all"
Requires-Dist: pydantic-settings (>=2.0.0,<3.0.0) ; extra == "api" or extra == "all"
Requires-Dist: pymongo (>=4.4.0,<5.0.0) ; extra == "api" or extra == "all"
Requires-Dist: pyspark (>=3.5.0,<4.0.0) ; extra == "spark" or extra == "all"
Requires-Dist: python-dotenv (>=1.0.0,<2.0.0)
Requires-Dist: scikit-optimize (>=0.9.0,<0.10.0) ; extra == "optimization" or extra == "all"
Requires-Dist: sqlalchemy (>=2.0.0,<3.0.0) ; extra == "database" or extra == "all"
Requires-Dist: typing-extensions (>=4.3.0,<5.0.0)
Requires-Dist: uvicorn[standard] (>=0.23.0,<0.24.0) ; extra == "api" or extra == "all"
Project-URL: Homepage, https://github.com/faustino125/tauro
Project-URL: Repository, https://github.com/faustino125/tauro
